{
    "outlined": {
        "height": "36px",
        "background": "transparent",
        "border": {
            "color": "rgba(0, 112, 121, 1)",
            "width": "1px",
            "radius": "4px"
        },
        "color": "rgba(0, 112, 121, 1)",
        "typography": {
            "color": "rgba(0, 112, 121, 1)",
            "fontFamily": "Equinor",
            "fontSize": "0.875rem",
            "fontWeight": 500,
            "letterSpacing": 0,
            "lineHeight": "1.143em",
            "textAlign": "center"
        },
        "spacing": {
            "left": "16px",
            "right": "16px"
        },
        "clickbound": "48px",
        "clickboundOffset": "6px",
        "focus": {
            "type": "dashed",
            "color": "rgba(0, 112, 121, 1)",
            "width": "2px",
            "gap": "8px"
        },
        "hoverBackground": "rgba(222, 237, 238, 1)",
        "pressedColor": "rgba(0, 0, 0, 0.2)"
    },
    "ghost": {
        "height": "36px",
        "background": "transparent",
        "border": {
            "color": "transparent",
            "width": "1px",
            "radius": "4px"
        },
        "color": "rgba(0, 112, 121, 1)",
        "typography": {
            "color": "rgba(0, 112, 121, 1)",
            "fontFamily": "Equinor",
            "fontSize": "0.875rem",
            "fontWeight": 500,
            "letterSpacing": 0,
            "lineHeight": "1.143em",
            "textAlign": "center"
        },
        "spacing": {
            "left": "16px",
            "right": "16px"
        },
        "clickbound": "48px",
        "clickboundOffset": "6px",
        "focus": {
            "type": "dashed",
            "color": "rgba(0, 112, 121, 1)",
            "width": "2px",
            "gap": "8px"
        },
        "hoverBackground": "rgba(222, 237, 238, 1)",
        "pressedColor": "rgba(0, 0, 0, 0.2)"
    },
    "ghost_icon": {
        "clickbound": "48px",
        "clickboundOffset": "",
        "focus": {
            "type": "dashed",
            "color": "rgba(0, 112, 121, 1)",
            "width": "2px",
            "gap": "8px"
        },
        "hoverBackground": "rgba(222, 237, 238, 1)",
        "pressedColor": "rgba(0, 0, 0, 0.2)"
    },
    "contained_right_icon": {
        "height": "36px",
        "background": "rgba(0, 112, 121, 1)",
        "border": {
            "color": "transparent",
            "width": "1px",
            "radius": "4px"
        },
        "color": "rgba(255, 255, 255, 1)",
        "typography": {
            "color": "rgba(255, 255, 255, 1)",
            "fontFamily": "Equinor",
            "fontSize": "0.875rem",
            "fontWeight": 500,
            "letterSpacing": 0,
            "lineHeight": "1.143em",
            "textAlign": "center"
        },
        "spacing": {
            "left": "16px",
            "right": "16px",
            "icon": "8px"
        },
        "clickbound": "48px",
        "clickboundOffset": "6px",
        "focus": {
            "type": "dashed",
            "color": "rgba(0, 112, 121, 1)",
            "width": "2px",
            "gap": "8px"
        },
        "hoverBackground": "rgba(0, 79, 85, 1)",
        "pressedColor": "rgba(0, 0, 0, 0.2)"
    },
    "outlined_right_icon": {
        "height": "36px",
        "background": "transparent",
        "border": {
            "color": "rgba(0, 112, 121, 1)",
            "width": "1px",
            "radius": "4px"
        },
        "color": "rgba(0, 112, 121, 1)",
        "typography": {
            "color": "rgba(0, 112, 121, 1)",
            "fontFamily": "Equinor",
            "fontSize": "0.875rem",
            "fontWeight": 500,
            "letterSpacing": 0,
            "lineHeight": "1.143em",
            "textAlign": "center"
        },
        "spacing": {
            "left": "16px",
            "icon": "8px"
        },
        "clickbound": "48px",
        "clickboundOffset": "6px",
        "focus": {
            "type": "dashed",
            "color": "rgba(0, 112, 121, 1)",
            "width": "2px",
            "gap": "8px"
        },
        "hoverBackground": "rgba(222, 237, 238, 1)",
        "pressedColor": "rgba(0, 0, 0, 0.2)"
    },
    "ghost_right_icon": {
        "height": "36px",
        "background": "transparent",
        "border": {
            "color": "transparent",
            "width": "1px",
            "radius": "4px"
        },
        "color": "rgba(0, 112, 121, 1)",
        "typography": {
            "color": "rgba(0, 112, 121, 1)",
            "fontFamily": "Equinor",
            "fontSize": "0.875rem",
            "fontWeight": 500,
            "letterSpacing": 0,
            "lineHeight": "1.143em",
            "textAlign": "center"
        },
        "spacing": {
            "left": "16px",
            "right": "16px",
            "icon": "8px"
        },
        "clickbound": "48px",
        "clickboundOffset": "6px",
        "focus": {
            "type": "dashed",
            "color": "rgba(0, 112, 121, 1)",
            "width": "2px",
            "gap": "8px"
        },
        "hoverBackground": "rgba(222, 237, 238, 1)",
        "pressedColor": "rgba(0, 0, 0, 0.2)"
    },
    "contained_left_icon": {
        "height": "36px",
        "background": "rgba(0, 112, 121, 1)",
        "border": {
            "color": "transparent",
            "width": "1px",
            "radius": "4px"
        },
        "color": "rgba(255, 255, 255, 1)",
        "typography": {
            "color": "rgba(255, 255, 255, 1)",
            "fontFamily": "Equinor",
            "fontSize": "0.875rem",
            "fontWeight": 500,
            "letterSpacing": 0,
            "lineHeight": "1.143em",
            "textAlign": "center"
        },
        "spacing": {
            "left": "16px",
            "right": "16px"
        },
        "clickbound": "48px",
        "clickboundOffset": "6px",
        "focus": {
            "type": "dashed",
            "color": "rgba(0, 112, 121, 1)",
            "width": "2px",
            "gap": "8px"
        },
        "hoverBackground": "rgba(0, 79, 85, 1)",
        "pressedColor": "rgba(0, 0, 0, 0.2)"
    },
    "outlined_left_icon": {
        "height": "36px",
        "background": "transparent",
        "border": {
            "color": "rgba(0, 112, 121, 1)",
            "width": "1px",
            "radius": "4px"
        },
        "color": "rgba(0, 112, 121, 1)",
        "typography": {
            "color": "rgba(0, 112, 121, 1)",
            "fontFamily": "Equinor",
            "fontSize": "0.875rem",
            "fontWeight": 500,
            "letterSpacing": 0,
            "lineHeight": "1.143em",
            "textAlign": "center"
        },
        "spacing": {
            "left": "16px",
            "right": "16px",
            "icon": "8px"
        },
        "clickbound": "48px",
        "clickboundOffset": "6px",
        "focus": {
            "type": "dashed",
            "color": "rgba(0, 112, 121, 1)",
            "width": "2px",
            "gap": "8px"
        },
        "hoverBackground": "rgba(222, 237, 238, 1)",
        "pressedColor": "rgba(0, 0, 0, 0.2)"
    },
    "ghost_left_icon": {
        "height": "36px",
        "background": "transparent",
        "border": {
            "color": "transparent",
            "width": "1px",
            "radius": "4px"
        },
        "color": "rgba(0, 112, 121, 1)",
        "typography": {
            "color": "rgba(0, 112, 121, 1)",
            "fontFamily": "Equinor",
            "fontSize": "0.875rem",
            "fontWeight": 500,
            "letterSpacing": 0,
            "lineHeight": "1.143em",
            "textAlign": "center"
        },
        "spacing": {
            "left": "16px",
            "right": "16px",
            "icon": "8px"
        },
        "clickbound": "48px",
        "clickboundOffset": "6px",
        "focus": {
            "type": "dashed",
            "color": "rgba(0, 112, 121, 1)",
            "width": "2px",
            "gap": "8px"
        },
        "hoverBackground": "rgba(222, 237, 238, 1)",
        "pressedColor": "rgba(0, 0, 0, 0.2)"
    },
    "contained": {
        "height": "36px",
        "background": "rgba(0, 112, 121, 1)",
        "border": {
            "color": "transparent",
            "width": "1px",
            "radius": "4px"
        },
        "color": "rgba(255, 255, 255, 1)",
        "typography": {
            "color": "rgba(255, 255, 255, 1)",
            "fontFamily": "Equinor",
            "fontSize": "0.875rem",
            "fontWeight": 500,
            "letterSpacing": 0,
            "lineHeight": "1.143em",
            "textAlign": "center"
        },
        "spacing": {
            "left": "16px",
            "right": "16px"
        },
        "clickbound": "48px",
        "clickboundOffset": "6px",
        "focus": {
            "type": "dashed",
            "color": "rgba(0, 112, 121, 1)",
            "width": "2px",
            "gap": "8px"
        },
        "hoverBackground": "rgba(0, 79, 85, 1)",
        "pressedColor": "rgba(0, 0, 0, 0.2)"
    }
}
